{
  "version": "20260717231401",
  "updated_at": "2026-07-17T23:14:01.322708+00:00",
  "total_symbols": 4,
  "symbols": {
    "XAUUSD": {
      "15min": {
        "status": "ok",
        "datetime": "2026-07-18 06:00:00",
        "open": 4015.95076,
        "high": 4015.95076,
        "low": 4012.35806,
        "close": 4013.06869,
        "ema50": 4002.742629284494,
        "ema200": 4013.0253538322063,
        "recent_high_20": 4022.84979,
        "recent_low_20": 4002.63215
      },
      "1h": {
        "status": "ok",
        "datetime": "2026-07-18 06:00:00",
        "open": 4015.95076,
        "high": 4015.95076,
        "low": 4012.35806,
        "close": 4013.06869,
        "ema50": 4008.849100127591,
        "ema200": 4054.1164477743087,
        "recent_high_20": 4022.84979,
        "recent_low_20": 3961.80817
      },
      "4h": {
        "status": "ok",
        "datetime": "2026-07-18 03:00:00",
        "open": 4015.87362,
        "high": 4018.48503,
        "low": 4002.87485,
        "close": 4013.06869,
        "ema50": 4049.1605716769027,
        "ema200": 4121.647543851004,
        "recent_high_20": 4097.88226,
        "recent_low_20": 3961.80817
      },
      "updated_at": "2026-07-17T20:15:23.486195+00:00"
    },
    "EURUSD": {
      "15min": {
        "status": "ok",
        "datetime": "2026-07-18 06:00:00",
        "open": 1.14408,
        "high": 1.14427,
        "low": 1.14396,
        "close": 1.14408,
        "ema50": 1.1437744541101251,
        "ema200": 1.1443804450023785,
        "recent_high_20": 1.14444,
        "recent_low_20": 1.14338
      },
      "1h": {
        "status": "ok",
        "datetime": "2026-07-18 06:00:00",
        "open": 1.14408,
        "high": 1.14427,
        "low": 1.14396,
        "close": 1.14408,
        "ema50": 1.1440916632624816,
        "ema200": 1.1430262533548592,
        "recent_high_20": 1.14522,
        "recent_low_20": 1.14239
      },
      "4h": {
        "status": "ok",
        "datetime": "2026-07-18 03:00:00",
        "open": 1.14379,
        "high": 1.14427,
        "low": 1.14338,
        "close": 1.14408,
        "ema50": 1.1430956783381225,
        "ema200": 1.1453533562399913,
        "recent_high_20": 1.14818,
        "recent_low_20": 1.14068
      },
      "updated_at": "2026-07-17T20:15:22.087074+00:00"
    },
    "GBPUSD": {
      "15min": {
        "status": "ok",
        "datetime": "2026-07-18 09:00:00",
        "open": 1.34509,
        "high": 1.34517,
        "low": 1.34501,
        "close": 1.34514,
        "ema50": 1.3452468062946996,
        "ema200": 1.3473031350396123,
        "recent_high_20": 1.34602,
        "recent_low_20": 1.34469
      },
      "1h": {
        "status": "ok",
        "datetime": "2026-07-18 09:00:00",
        "open": 1.34509,
        "high": 1.34517,
        "low": 1.34501,
        "close": 1.34514,
        "ema50": 1.3460831173812389,
        "ema200": 1.342823483018058,
        "recent_high_20": 1.34804,
        "recent_low_20": 1.34245
      },
      "4h": {
        "status": "ok",
        "datetime": "2026-07-18 07:00:00",
        "open": 1.34528,
        "high": 1.34544,
        "low": 1.34469,
        "close": 1.34514,
        "ema50": 1.3426278090139852,
        "ema200": 1.3356086434462855,
        "recent_high_20": 1.35583,
        "recent_low_20": 1.33688
      },
      "updated_at": "2026-07-17T23:14:01.164574+00:00"
    },
    "USDJPY": {
      "15min": {
        "status": "ok",
        "datetime": "2026-07-18 09:00:00",
        "open": 162.43433,
        "high": 162.44635,
        "low": 162.40141,
        "close": 162.43955,
        "ema50": 162.42373360450355,
        "ema200": 162.32788792944459,
        "recent_high_20": 162.47808,
        "recent_low_20": 162.36334
      },
      "1h": {
        "status": "ok",
        "datetime": "2026-07-18 09:00:00",
        "open": 162.43433,
        "high": 162.44635,
        "low": 162.40141,
        "close": 162.43955,
        "ema50": 162.34597200486874,
        "ema200": 162.1856827263746,
        "recent_high_20": 162.52465,
        "recent_low_20": 162.16633
      },
      "4h": {
        "status": "ok",
        "datetime": "2026-07-18 07:00:00",
        "open": 162.411,
        "high": 162.46649,
        "low": 162.36334,
        "close": 162.43955,
        "ema50": 162.1684848301286,
        "ema200": 161.57116401633533,
        "recent_high_20": 162.54807,
        "recent_low_20": 161.89685
      },
      "updated_at": "2026-07-17T23:14:01.322695+00:00"
    }
  }
}