{
  "version": "20260711060409",
  "updated_at": "2026-07-11T06:04:09.242910+00:00",
  "total_symbols": 4,
  "symbols": {
    "XAUUSD": {
      "15min": {
        "status": "ok",
        "datetime": "2026-07-11 07:30:00",
        "open": 4111.44515,
        "high": 4111.63473,
        "low": 4111.38783,
        "close": 4111.5285,
        "ema50": 4107.412773848847,
        "ema200": 4099.287487422635,
        "recent_high_20": 4120.82252,
        "recent_low_20": 4097.18533
      },
      "1h": {
        "status": "ok",
        "datetime": "2026-07-11 07:00:00",
        "open": 4119.46069,
        "high": 4120.42164,
        "low": 4110.97947,
        "close": 4111.5285,
        "ema50": 4108.353131317814,
        "ema200": 4115.449915693657,
        "recent_high_20": 4133.93964,
        "recent_low_20": 4076.64085
      },
      "4h": {
        "status": "ok",
        "datetime": "2026-07-11 07:00:00",
        "open": 4119.46069,
        "high": 4120.42164,
        "low": 4110.97947,
        "close": 4111.5285,
        "ema50": 4115.521027968852,
        "ema200": 4194.311468079726,
        "recent_high_20": 4148.01393,
        "recent_low_20": 4022.20256
      },
      "updated_at": "2026-07-10T21:34:32.951942+00:00"
    },
    "EURUSD": {
      "15min": {
        "status": "ok",
        "datetime": "2026-07-11 07:30:00",
        "open": 1.1415,
        "high": 1.1418,
        "low": 1.14143,
        "close": 1.14178,
        "ema50": 1.1424262195656196,
        "ema200": 1.1426415672437358,
        "recent_high_20": 1.14367,
        "recent_low_20": 1.14078
      },
      "1h": {
        "status": "ok",
        "datetime": "2026-07-11 07:00:00",
        "open": 1.14154,
        "high": 1.1421,
        "low": 1.14078,
        "close": 1.14178,
        "ema50": 1.1428581404675948,
        "ema200": 1.1426997353480157,
        "recent_high_20": 1.14605,
        "recent_low_20": 1.14078
      },
      "4h": {
        "status": "ok",
        "datetime": "2026-07-11 07:00:00",
        "open": 1.14154,
        "high": 1.1421,
        "low": 1.14078,
        "close": 1.14178,
        "ema50": 1.1425350084363226,
        "ema200": 1.1478198082607167,
        "recent_high_20": 1.14605,
        "recent_low_20": 1.13915
      },
      "updated_at": "2026-07-10T21:34:32.343551+00:00"
    },
    "GBPUSD": {
      "15min": {
        "status": "ok",
        "datetime": "2026-07-11 16:00:00",
        "open": 1.33973,
        "high": 1.3399,
        "low": 1.33973,
        "close": 1.33988,
        "ema50": 1.340139557652433,
        "ema200": 1.3405487634399682,
        "recent_high_20": 1.34039,
        "recent_low_20": 1.33931
      },
      "1h": {
        "status": "ok",
        "datetime": "2026-07-11 16:00:00",
        "open": 1.33973,
        "high": 1.3399,
        "low": 1.33973,
        "close": 1.33988,
        "ema50": 1.340406779411195,
        "ema200": 1.3370511653913668,
        "recent_high_20": 1.34371,
        "recent_low_20": 1.33931
      },
      "4h": {
        "status": "ok",
        "datetime": "2026-07-11 15:00:00",
        "open": 1.34021,
        "high": 1.34039,
        "low": 1.33955,
        "close": 1.33988,
        "ema50": 1.3368554369427634,
        "ema200": 1.3345091245944707,
        "recent_high_20": 1.34517,
        "recent_low_20": 1.33239
      },
      "updated_at": "2026-07-11T06:04:09.088483+00:00"
    },
    "USDJPY": {
      "15min": {
        "status": "ok",
        "datetime": "2026-07-11 16:00:00",
        "open": 161.73671,
        "high": 161.74024,
        "low": 161.72838,
        "close": 161.738,
        "ema50": 161.72218728215208,
        "ema200": 161.99318151562647,
        "recent_high_20": 161.76919,
        "recent_low_20": 161.68715
      },
      "1h": {
        "status": "ok",
        "datetime": "2026-07-11 16:00:00",
        "open": 161.73671,
        "high": 161.74024,
        "low": 161.72838,
        "close": 161.738,
        "ema50": 161.8879259711177,
        "ema200": 161.87633279249198,
        "recent_high_20": 161.92466,
        "recent_low_20": 161.30183
      },
      "4h": {
        "status": "ok",
        "datetime": "2026-07-11 15:00:00",
        "open": 161.73597,
        "high": 161.74809,
        "low": 161.68715,
        "close": 161.738,
        "ema50": 161.9230294954963,
        "ema200": 161.22828633200595,
        "recent_high_20": 162.71291,
        "recent_low_20": 161.30183
      },
      "updated_at": "2026-07-11T06:04:09.242898+00:00"
    }
  }
}